scopedconfig/__init__.py
scopedconfig/config.py
scopedconfig/error.py
scopedconfig/lexer.py
scopedconfig/parser.py
scopedconfig-0.0.0.dist-info/LICENSE.rst
scopedconfig-0.0.0.dist-info/METADATA
scopedconfig-0.0.0.dist-info/WHEEL
scopedconfig-0.0.0.dist-info/top_level.txt
scopedconfig-0.0.0.dist-info/zip-safe
scopedconfig-0.0.0.dist-info/RECORD
